keyhole/__init__.py
keyhole/__main__.py
keyhole_comm-1.13.0.dist-info/licenses/LICENSE.txt
keyhole_comm-1.13.0.dist-info/METADATA
keyhole_comm-1.13.0.dist-info/WHEEL
keyhole_comm-1.13.0.dist-info/top_level.txt
keyhole_comm-1.13.0.dist-info/RECORD
