Metadata-Version: 2.4
Name: keyhole-comm
Version: 1.13.0
Summary: Low-effort serial communication, e.g. for talking to devices that use the Arduino-IDE Keyhole library
Home-page: https://bitbucket.org/jezhill/Keyhole
Author: Jeremy Hill
Author-email: jezhill@gmail.com
License: CC0
License-File: LICENSE.txt
Requires-Dist: pyserial
Dynamic: author
Dynamic: author-email
Dynamic: description
Dynamic: description-content-type
Dynamic: home-page
Dynamic: license
Dynamic: license-file
Dynamic: requires-dist
Dynamic: summary
